{
  "slug": "the-myth-of-sisyphus",
  "title": "Book Review: The Myth of Sisyphus &#8211; Albert Camus",
  "date": "2020-10-30",
  "url": "https://eternalisedofficial.com/2020/10/30/the-myth-of-sisyphus/",
  "categories": [
    "Camus",
    "Existentialism"
  ],
  "content": "One of Albert Camus' most famous and important works is the philosophical essay The Myth of Sisyphus . It starts off with a powerful and thought-provoking statement: &#8220;There is but one truly serious philosophical problem and that is suicide. Judging whether life is or is not worth living amounts to answering the fundamental question of philosophy.&#8221; Rating \u2b50 \u2b50 \u2b50 \u2b50 \u2b50 Rating: 5 out of 5. Physical suicide tends to happen without going through reflection, &#8220; one evening the person pulls the trigger or jumps. &#8221; Killing oneself is a sort of confession, that life is too much, that it is incomprehensible, or that it is not worth the trouble. Dying voluntarily implies the absence of any profound reason for living and the uselessness of suffering. The novel presents itself through an absurdist lens. The Absurd is the conflict between the human tendency to seek inherent value and meaning in life, and the human inability to find any meaning in a purposeless, meaningless, and irrational universe, with the \u201cunreasonable silence\u201d of the universe in response. Trying to define this, is like water slipping through one\u2019s fingers. However, this world in itself is not absurd, what is absurd is our relationship with the universe , which is irrational. The absurd depends as much on man as on the world. It is all that links them together. Thus, the universe and the human mind do not each separately cause the Absurd, but rather, the Absurd arises by the contradictory nature of the two existing simultaneously. Another important aspect of this book is that it is atheistic in nature, he calls the Absurd, which we all live in to be &#8220;sin without God.&#8221; For Camus, believing in some ready-made belief system (practically all of the world's religion) is one of the most common ways of &#8216;philosophical suicide' . We believe in a hypothetical belief system, immediately alleviating us from these insecurities, at the cost of committing a sort of mental suicide by shutting down our mental faculties. There are also secular ways of committing this act, such as escaping into the world of entertainment. However, in a world suddenly divested of illusions, man feels an alien. Without hope of a promised land. This divorce between man and his life, the actor and his setting, is properly the feeling of absurdity. Moreover, our daily life is also absurd: &#8220;Rising, tram, four hours in the office or factory, meal, tram four hours of work, meal, sleep and Monday, Tuesday, Wednesday, Thursday, Friday and Saturday, according to the same rhythm - this path is easily followed most of the time. But one day the &#8216; why &#8216; arises and everything begins in that weariness tinged with amazement.&#8221; Thus, we all live in an absurd freedom, and to become lucid and conscious of it is to revolt , which is the only coherent philosophical position: &#8220;It [Revolt] is a constant confrontation between man and his own obscurity. It is an insistence upon an impossible transparency. It challenges the world new every second. Just as danger provided man with the unique opportunity of seizing awareness, so metaphysical revolt extends awareness to the whole of experience.&#8221; Suicide is never an option for the Absurd man, much like the leap of faith, it is acceptance at its extreme, it would be a way of going along with our absurd condemnation, by implicitly affirming that life is really intolerably absurd and that suicide is our only option. The contrary of suicide is man condemned to death, in constant lucidity of his own absurd nature with the passionate flames of human revolt. This recognition gives life meaning, as we are truly free &#8220;to live without appeal &#8220; , as he puts it, a philosophical move to define absolutes and universals subjectively, rather than objectively. \u201cThe only way to deal with an unfree world is to become so absolutely free that your very existence is an act of rebellion.\u201d He draws from the absurd three consequences: revolt , freedom and passion . Essentially, man is his own end. And he is his only end. If he aims to be something, it is in this life: &#8220;The flames of earth are surely worth celestial perfumes.&#8221; So, where does the title The Myth of Sisyphus come from? Camus associates our condemnation to the absurd to the mythological character of Sisyphus , a man condemned by the gods to a lifetime of rolling a boulder up a hill, a back-breaking and gruelling labour, only to reach the top of the hill and have the boulder inevitably roll back down to the bottom for him to start all over again, condemned to a lifetime of pain and anguish and working hard only to have his efforts be completely futile in the end. It isn\u2019t the repetitive and futile nature of human existence per se that makes it absurd. What really makes our human existence absurd is our consciousness of our Sisyphean condemnation when we avoid the trap of philosophical suicide. In perhaps one of his most celebrated quotes, Camus states that: \u201cThe struggle itself towards the heights is enough to fill a man\u2019s heart. One must imagine Sisyphus happy. \u201d Camus adds that there may be a moment when Sisyphus is walking back down the hill when he is briefly free, when he is &#8220;superior to his fate. He is stronger than his rock &#8220;. Sisyphus then, is both a prisoner and rebel. Unlike many existentialists, Camus is an earth-loving and sensitive man who loves his native home of Algeria: its sunlight, nature and the beauty of the race. At the end of the book, he writes short essays such as the Summer in Algiers where he states: &#8220;For if there is a sin against life, it consists perhaps not so much in despairing of life as in hoping for another life and in eluding the implacable grandeur of this life.&#8221; And Return to Tipasa , where he writes: &#8220;In the middle of winter, I at last discovered that there was in me an invincible summer. &#8220; And finally : &#8220; There is thus a will to live without rejecting anything of life, which is the virtue I honor most in this world .&#8221; \ud83d\udcdaThe Book As an Amazon Associate, I earn from qualifying purchases at no additional cost to you. Sign up with your e-mail to get a notification of the latest posts! Enter your email address Sign Up Watch The Full Video \ud83d\udcfa Greatest Philosophers In History | Albert Camus Camus gave rise to Absurdism. He is also considered to be an Existentialist. This video explores his main ideas: The Absurd, Revolt and Rebellion , as well as his most notable works: The Stranger , The Myth of Sisyphus, The Rebel , The Plague , and The Fall . He received the Nobel Prize in Literature in 1957. Support Eternalised Ko-fi Patreon YouTube Buy Official Merch Redbubble Spring &#8220;A room without books is like a body without a soul.&#8221; \u2014 Cicero Great Books List Discord Community Join Discord Follow Eternalised on social media! YouTube Pinterest Facebook Instagram Twitter Liked it? Take a second to support Eternalised on Patreon! Related Related Posts: The Inner Work Archive Essays in Psychology, Spirituality & Philosophy Favourite Quotes (Patrons Only) Artwork in videos (Patrons Only)",
  "word_count": 1216,
  "images": [
    {
      "url": "https://i0.wp.com/eternalisedofficial.com/wp-content/uploads/2020/10/as-3.png?fit=680%2C680&amp;ssl=1",
      "alt": "",
      "local_path": "content/research/eternalised/the-myth-of-sisyphus/art/art_000.png"
    },
    {
      "url": "https://i0.wp.com/eternalisedofficial.com/wp-content/plugins/patron-button-and-widgets-by-codebard/images/become_a_patron_button.png?w=750&#038;ssl=1",
      "alt": "",
      "local_path": "content/research/eternalised/the-myth-of-sisyphus/art/art_001.png"
    },
    {
      "url": "https://i0.wp.com/eternalisedofficial.com/wp-content/uploads/2025/10/61-V6G1L6UL._SL1360_.jpg?resize=150%2C150&amp;ssl=1",
      "alt": "",
      "local_path": "content/research/eternalised/the-myth-of-sisyphus/art/art_002.jpg"
    },
    {
      "url": "https://i0.wp.com/eternalisedofficial.com/wp-content/uploads/2025/01/8347b3a8-6cf7-8d0e-0f1f-f66a3f2fb7b6-2.jpg?resize=150%2C150&amp;ssl=1",
      "alt": "",
      "local_path": "content/research/eternalised/the-myth-of-sisyphus/art/art_003.jpg"
    },
    {
      "url": "https://i0.wp.com/eternalisedofficial.com/wp-content/uploads/2023/12/Alexander-Pushkin-at-the-Seashore-1896-Leonid-Osipovic-Pasternak.jpg?resize=150%2C150&amp;ssl=1",
      "alt": "",
      "local_path": "content/research/eternalised/the-myth-of-sisyphus/art/art_004.jpg"
    },
    {
      "url": "https://i0.wp.com/eternalisedofficial.com/wp-content/uploads/2025/03/9780367708696-3012128010.jpg?resize=150%2C150&amp;ssl=1",
      "alt": "",
      "local_path": "content/research/eternalised/the-myth-of-sisyphus/art/art_005.jpg"
    },
    {
      "url": "https://eternalisedofficial.com/wp-content/plugins/patron-button-and-widgets-by-codebard/images/become_a_patron_button.png",
      "alt": "",
      "local_path": "content/research/eternalised/the-myth-of-sisyphus/art/art_006.png"
    }
  ],
  "images_downloaded": 7
}