{
  "id": "bridge-pubmed-preventive-effect-of-one-session-brief-focused-attention-meditation-on-state-fat",
  "type": "type-b-essay",
  "title": "Bridge Essay: Preventive effect of one-session brief focused attention meditation on state fat",
  "source_work": "work:t2-pubmed-preventive-effect-of-one-session-brief-focused-attention-meditation-on-state-fat",
  "phase": "phase-9",
  "phase_name": "Language/Mantra",
  "tags": [
    "frontier-science",
    "bridge-paper",
    "phase-9"
  ],
  "body": [
    {
      "kind": "ai",
      "text": "This bridge paper connects the esoteric/philosophical concept of **Language/Mantra** with mechanistic science from PubMed/MEDLINE."
    },
    {
      "kind": "ai",
      "text": "**Bridge rationale:** Phase 9 (Language/Mantra) quality improvement v2."
    },
    {
      "kind": "summary",
      "text": "**Preventive effect of one-session brief focused attention meditation on state fatigue: Resting state functional magnetic resonance imaging study.** \u2014 NeuroImage (2024). PMID: . DOI: 10.1016/j.neuroimage.2024.120709. Score: 19. The extended practice of meditation may reduce the influence of state fatigue by changing neurocognitive processing. However, little is known about the preventive effects of one-session brief focused attention meditation (FAM) on state fatigue in healthy participants or its potential neural mechanisms. This study examined the preventive effects of one-session brief FAM on state fatigue and its neural correlates using resting-state functional MRI (rsfMRI) measurements. We randomly divided 56 medi"
    }
  ],
  "notes": "Auto-acquired from PubMed/MEDLINE on 2026-07-12. Phase 9 quality improvement v2."
}