{
  "id": "bridge-pubmed-the-interpersonal-neurobiology-of-intersubjectivity",
  "title": "Bridge Paper: The Interpersonal Neurobiology of Intersubjectivity.",
  "author": "Frontier Science / Hermes T2",
  "type": "bridge_essay",
  "source_ids": [
    "t2-pubmed-the-interpersonal-neurobiology-of-intersubjectivity"
  ],
  "concepts": [
    "phase-17",
    "frontier-science",
    "bridge-paper"
  ],
  "prerequisites": [],
  "body": [
    {
      "kind": "ai",
      "text": "This bridge paper connects the esoteric/philosophical concept of **Social Incarnation** with mechanistic science from PubMed/MEDLINE."
    },
    {
      "kind": "ai",
      "text": "**Bridge thesis:** Social Incarnation \u2014 intersubjectivity, embodied empathy, social predictive processing."
    },
    {
      "kind": "ai",
      "text": "**Phase context:** intersubjectivity, embodied empathy, predictive processing social cognition"
    },
    {
      "kind": "summary",
      "text": "Paper: The Interpersonal Neurobiology of Intersubjectivity.\nDOI: 10.3389/fpsyg.2021.648616\nAbstract: In 1975, Colwyn Trevarthen first presented his groundbreaking explorations into the early origins of human intersubjectivity. His influential model dictates that, during intimate and playful spontaneous face-to-face protoconversations, the emotions of both the 2-3-month-old infant and mother are nonverbally communicated, perceived, mutually regulated, and intersubjectively shared. This primordial basic interpersonal interaction is expressed in synchronized rhythmic-turn-taking transactions that "
    }
  ],
  "notes": "Auto-acquired from PubMed/MEDLINE on 2026-07-11. Phase 17 (Social Incarnation).",
  "phases": [
    "phase-17-social-incarnation"
  ]
}