{
  "slug": "the-absurd",
  "title": "The Absurd \u2013 Camus, Kierkegaard &amp; Dostoevsky | Existentialism",
  "date": "2020-11-20",
  "url": "https://eternalisedofficial.com/2020/11/20/the-absurd/",
  "categories": [
    "Camus",
    "Dostoevsky",
    "Kierkegaard",
    "Existentialism"
  ],
  "content": "Albert Camus\u2019 views contributed to the rise of the philosophy known as Absurdism, he defines the Absurd \u201cas the conflict between the human tendency to seek inherent value and meaning in life, and the human inability to find any meaning in a purposeless, meaningless, and irrational universe, with the \u2018unreasonable silence\u2019 of the universe in response.\u201d However, this world in itself is not absurd, what is absurd is our relationship with the universe, which is irrational. Camus is considered to be an existentialist, even though he firmly rejected the term throughout his lifetime. He is properly categorised as an atheist existentialist. However, he would also disagree with this label. In his notebooks, he presents the following contradictory statement: \u201cI do not believe in God and I am not an atheist.\u201d This reflects the notion of the Absurd. The search of the possibility of the existence of God is humanly impossible, but this also entails that the proof that God does not exist is impossible too. He writes in The Myth of Sisyphus: \u201cIn a universe suddenly divested of illusions and lights, man feels an alien, a stranger. His exile is without remedy since he is deprived of the memory of a lost home or the hope of a promised land. This divorce between man and his life, the actor and his setting, is properly the feeling of absurdity.\u201d The Myth of Sisyphus is a fierce expression of the Absurd. It starts off with a powerful and thought-provoking statement: \u201cThere is but one truly serious philosophical problem and that is suicide. Judging whether life is or is not worth living amounts to answering the fundamental question of philosophy.\u201d Apart from the physical act of suicide, he talks about \u201cphilosophical suicide\u201d, where we accept something as true that isn\u2019t convincing but is convenient and easy for us to believe in. Such as believing in some ready-made belief system, which is practically all of the world\u2019s religion. This is the complete opposite of Danish philosopher S\u00f8ren Kierkegaard\u2019s leap of faith. Kierkegaard described himself as a Christian, although he despised the established church, which in his view, made individuals lazy in their religion, many of the citizens were officially \u201cChristians\u201d without having any idea what it meant to be a Christian. The world is absurd, and we must live in it. He says: \u201cAs I grew up, I opened my eyes and saw the real world, I began to laugh and I haven\u2019t stopped since\u201d. Kierkegaard states that \u201canxiety is the dizziness of freedom\u201d. We enjoy a freedom that is both appealing and terrifying. In The Sickness Unto Death , he writes: \u201cFor the self is a synthesis in which the finite is the limiting factor, and the infinite the expanding factor.\u201d In other words, we are made of two opposites: the finite and the infinite. He considers the finite as actuality, as one\u2019s reality, while the infinite corresponds to possibility, to be able to choose. We lose ourselves in the infinite when considering the infinite possibilities in our life and our limited power of choice over them. We have an infinite number of possibilities and when we have to choose one, we become overwhelmed at the sheer amount of them. One may possess the ability to freely act, but if one never uses it and gets lost in the infinite, daydreaming about an endless sea of possibilities, one is effectively not capable of freely acting. In essence, we are obsessed with what we can potentially become, but in reality, never become anything. On the other hand, we lose ourselves in the finite when we don\u2019t consider enough possibilities and just mindlessly go around the demands of culture and social expectations, because we feel imprisoned in an inescapable environment where no alternatives exist, \u201cone becomes an imitation, a number, a cipher in the crowd.\u201d The scary part is that most people are less aware of this, they see everything they do as their own choice. However, some people live a complete lie. They live because of what their family, friends and society tell them that\u2019s what one does. Kierkegaard suggests that the only way out of this is to take a leap of faith towards Christianity, the ultimate irrational experience, which is the most rational thing to do. This is the quintessential subjective experience. Although Camus states that he cannot know that God does not exist, he is determined to believe that God cannot exist, he opposes religious faith. His work can be seen as a reply to Kierkegaard and Russian novelist Fyodor Dostoevsky , and the paradox whereby those two writers acknowledge the absurdity of the universe only to embrace more strongly the scandal of belief in God. Camus was very influenced Dostoevsky. He discovered a powerful and vital source of inspiration in two novels in particular, Demons and The Brothers Karamazov. The atheistic spirit of Ivan Karamazov proved for Camus the most attractive of all of his characters. His statement that \u201cIf God is dead, then all is permitted\u201d resonated with him. However, he criticises both Kierkegaard and Dostoevsky for their leap into irrational faith. Dostoevsky ultimately turned away from the absurd by embracing Christianity, which Camus sees an invalid response to the absurd. In Demons, Dostoevsky explores the idea that either there is a God, a life after death and life has a meaning, or life has no meaning and everything we do is pointless, it is little more than a cruel joke. Kirillov is a character from Demons who commits a sort of \u201clogical suicide\u201d. He feels that God is necessary and that he must exist. But he knows that he does not and cannot exist. He exclaims: \u201cwhy do you not realise that this is sufficient reason for killing oneself?\u201d And finally, he prepares his deed with a mixed feeling of revolt and freedom. \u201cI shall kill myself in order to assert my insubordination, my new and dreadful liberty.\u201d Kirillov is consequently an absurd character: he kills himself. He kills himself to become god. His reasoning being that: if God does not exist, he becomes god, and if God does not exist, he must kill himself. He must therefore kill himself to become god. Thus, for Kirillov, as for Nietzsche: to kill God is to become god oneself. However, if God does not exist, one is free, why kill oneself and leave this world after having won freedom? Isn\u2019t this contradictory? Kirillov is well aware of this, he kills himself out of love of humanity, he shows his brothers a difficult path on which he will be the first, it is a pedagogical suicide. Kirillov\u2019s pistol-shot will be the signal for the last revolution. Thus, it is not despair that urges him to death but love of his neighbour for his own sake. His last words: \u201cAll is well\u201d. While Dostoevsky proposes suicide as the only logical response to an awareness that God does not exist, Camus proposes that the man without God must not kill himself, but realise instead that he is condemned to death, and live his life embracing the absurdity of that knowledge. The ultimate Absurd Man for Camus is best expressed in the mythological character of Sisyphus, a man condemned by the gods to a lifetime of rolling a boulder up a hill, only to reach the top of the hill and have the boulder inevitably roll back down to the bottom for him to start all over again, condemned to a lifetime of pain and anguish and working hard only to have his efforts be completely futile in the end. What really makes our human existence absurd is our consciousness of our Sisyphean condemnation when we avoid the trap of philosophical suicide. In perhaps one of his most celebrated quotes, Camus states that: \u201cThe struggle itself towards the heights is enough to fill a man\u2019s heart. One must imagine Sisyphus happy.\u201d Camus later adds that there may be a moment when Sisyphus is walking back down the hill when he is briefly free, when he is &#8220;superior to his fate. He is stronger than his rock&#8221; . Sisyphus then, is both a prisoner and a rebel. Thus, we all live in an absurd freedom, and to become lucidly aware and conscious of it is to revolt, to affirm life and continue, which is the only coherent philosophical position: \u201cIt is a constant confrontation between man and his own obscurity. It is an insistence upon an impossible transparency. It challenges the world anew every second. Just as danger provided man with the unique opportunity of seizing awareness, so metaphysical revolt extends awareness to the whole of experience.\u201d To revolt is to say no to one\u2019s own absurd existence and say yes to some other more desirable existence. Thus: \u201cThe only way to deal with an unfree world is to become so absolutely free that your very existence is an act of rebellion.\u201d Suicide is never an option for the Absurd Man, much like the leap of faith, it is acceptance at its extreme, it would be a way of going along with our absurd condemnation, by implicitly affirming that life is really intolerably absurd and that suicide is our only option. The contrary of suicide is man condemned to death, in constant lucidity of his own absurd nature with the passionate flames of human revolt. This recognition gives life meaning, as we are truly free, we are to \u201clive without appeal\u201c as he puts it, defining absolutes and universals subjectively, rather than objectively. Camus writes with great delicacy. What moves us is not that Camus\u2019 emblem of the absurd is so entirely metaphorical, but the spectacle of his belief; that he believes in it so fiercely, and so sympathetically describes his fate and revolt, that Sisyphus appears to be real to Camus, and becomes almost actual for us. This is the quality of Camus\u2019 thought, and it is why he is such a powerful novelist: he takes religious terms, turns them into secular metaphor, and then, appears to reconvert them back into a usable reality. What he does, in fact, is act as if they were real while using them metaphorically. Christianity extends life in an eternal heaven. Camus wants to extend life on earth. He writes that \u201c the present and the succession of presents before a constantly conscious soul is the ideal of the absurd man\u201d. This is Camus\u2019 eternity: an endless repetition of presents. However, is Camus\u2019 rebellion only metaphorical? Perhaps not. In The Drowned and the Saved, Primo Levi writes about his time spend in a concentration camp, where he was faced with a temptation to pray, instinct with Camus\u2019 language of lucidity and absurdity, it is an extraordinarily \u201crebellious\u201d passage of secular writing: \u201cI too entered the Lager as a non-believer, and as a non-believer I was liberated and have lived to this day; actually, the experience of the Lager with its frightful iniquity has confirmed me in my laity. It has prevented me, and still prevents me, from conceiving of any form of providence of transcendent justice\u2026 I must nevertheless admit that I experienced (and again only once) the temptation to yield, to seek refuge in prayer. This happened in the October of 1944, in the one moment in which I lucidly perceived the imminence of death. Naked and compressed among my naked companions with my index card in hand, I was waiting to file past the \u2018commission\u2019 that with one glance would decide whether I should immediately go into the gas chamber or was instead strong enough to go on working. For one instant I felt the need to ask for help and asylum; then, despite my anguish, equanimity prevailed: you do not change the rules of the game at the end of the match, nor when you are losing. A prayer under these conditions would have been not only absurd (what rights could I claim? and from whom?) but blasphemous, obscene, with the greatest impiety of which a non-believer is capable. I rejected the temptation: I knew that otherwise were I to survive, I would have to be ashamed of it.\u201d \ud83d\udcdaRecommended Reading As an Amazon Associate, I earn from qualifying purchases at no additional cost to you. \ud83d\udcfaWatch The Full Video!\ud83e\udde0 The Absurd \u2013 Camus, Kierkegaard Dostoevsky | Existentialism This video explores the concept of The Absurd of Camus, Kierkegaard, and Dostoevsky as well as the differences between these three existentialists. Support Eternalised Ko-fi Patreon YouTube Buy Official Merch Redbubble Spring &#8220;A room without books is like a body without a soul.&#8221; \u2014 Cicero Great Books List Discord Community Join Discord Follow Eternalised on social media! YouTube Pinterest Facebook Instagram Twitter Liked it? Take a second to support Eternalised on Patreon! Related Related Posts: The Inner Work Archive Essays in Psychology, Spirituality & Philosophy Favourite Quotes (Patrons Only) Artwork in videos (Patrons Only)",
  "word_count": 2147,
  "images": [
    {
      "url": "https://i0.wp.com/eternalisedofficial.com/wp-content/uploads/2020/11/untitled-1.png?fit=795%2C440&amp;ssl=1",
      "alt": "",
      "local_path": "content/research/eternalised/the-absurd/art/art_000.png"
    },
    {
      "url": "https://i0.wp.com/eternalisedofficial.com/wp-content/uploads/2020/11/camus.jpg?resize=750%2C987&#038;ssl=1",
      "alt": "",
      "local_path": "content/research/eternalised/the-absurd/art/art_001.jpg"
    },
    {
      "url": "https://i0.wp.com/eternalisedofficial.com/wp-content/uploads/2020/11/kierke2.jpg?resize=750%2C720&#038;ssl=1",
      "alt": "",
      "local_path": "content/research/eternalised/the-absurd/art/art_002.jpg"
    },
    {
      "url": "https://i0.wp.com/eternalisedofficial.com/wp-content/uploads/2020/11/dost.jpg?resize=750%2C938&#038;ssl=1",
      "alt": "",
      "local_path": "content/research/eternalised/the-absurd/art/art_003.jpg"
    },
    {
      "url": "https://i0.wp.com/eternalisedofficial.com/wp-content/uploads/2020/11/kiri.jpg?resize=750%2C1144&#038;ssl=1",
      "alt": "",
      "local_path": "content/research/eternalised/the-absurd/art/art_004.jpg"
    },
    {
      "url": "https://i0.wp.com/eternalisedofficial.com/wp-content/plugins/patron-button-and-widgets-by-codebard/images/become_a_patron_button.png?w=750&#038;ssl=1",
      "alt": "",
      "local_path": "content/research/eternalised/the-absurd/art/art_005.png"
    },
    {
      "url": "https://i0.wp.com/eternalisedofficial.com/wp-content/uploads/2025/10/61-V6G1L6UL._SL1360_.jpg?resize=150%2C150&amp;ssl=1",
      "alt": "",
      "local_path": "content/research/eternalised/the-absurd/art/art_006.jpg"
    },
    {
      "url": "https://i0.wp.com/eternalisedofficial.com/wp-content/uploads/2025/01/8347b3a8-6cf7-8d0e-0f1f-f66a3f2fb7b6-2.jpg?resize=150%2C150&amp;ssl=1",
      "alt": "",
      "local_path": "content/research/eternalised/the-absurd/art/art_007.jpg"
    },
    {
      "url": "https://i0.wp.com/eternalisedofficial.com/wp-content/uploads/2023/12/Alexander-Pushkin-at-the-Seashore-1896-Leonid-Osipovic-Pasternak.jpg?resize=150%2C150&amp;ssl=1",
      "alt": "",
      "local_path": "content/research/eternalised/the-absurd/art/art_008.jpg"
    },
    {
      "url": "https://i0.wp.com/eternalisedofficial.com/wp-content/uploads/2025/03/9780367708696-3012128010.jpg?resize=150%2C150&amp;ssl=1",
      "alt": "",
      "local_path": "content/research/eternalised/the-absurd/art/art_009.jpg"
    },
    {
      "url": "https://eternalisedofficial.com/wp-content/plugins/patron-button-and-widgets-by-codebard/images/become_a_patron_button.png",
      "alt": "",
      "local_path": "content/research/eternalised/the-absurd/art/art_010.png"
    }
  ],
  "images_downloaded": 11
}