{
  "id": "art_alchemy_e294",
  "title": "A254. Engraving from Dorn, Gerhardt Aurora, Basel, 1577.",
  "artist": "Dorn",
  "date": "1577",
  "source_url": "https://www.alchemywebsite.com",
  "image_url": "/art/alchemy/gallery-8/A294.jpg",
  "local_file": "content/sources/occult/alchemy/emblems/gallery-8/A294.jpg",
  "license": "Public Domain",
  "description": "A254. Engraving from Dorn, Gerhardt Aurora, Basel, 1577.",
  "original_metadata": {
    "file": "A294.jpg",
    "caption": "A254. Engraving from Dorn, Gerhardt <em>Aurora</em>, Basel, 1577.",
    "source": "alchemywebsite.com",
    "gallery": 8,
    "gallery_position": 294
  },
  "concepts": [
    "Transformation",
    "Divine Power"
  ],
  "visual_motifs": [
    "spagyric"
  ],
  "style": [
    "illuminated_manuscript",
    "renaissance"
  ],
  "used_in": [],
  "motion_notes": [
    "slow_zoom"
  ],
  "notes": "Gallery 8, position 294/320. From alchemywebsite.com.",
  "mood": [
    "visionary",
    "illuminated",
    "mystical"
  ],
  "color_palette": [
    "gold",
    "blue",
    "red",
    "green"
  ],
  "entities_depicted": [
    "paracelsus"
  ],
  "composition": "single_figure"
}