{
  "id": "art_aic_e_12_english_drawing_room_of_the_georgian_period_c",
  "title": "E-12: English Drawing Room of the Georgian Period, c. 1800",
  "image_url": "https://www.artic.edu/iiif/2/25d5f01c-e2f2-4d7b-db3f-d0b38987e1f0/full/843,/0/default.jpg",
  "artist": "Narcissa Niblack Thorne",
  "date": "c. 1937",
  "source_url": "https://www.artic.edu/artworks/43721",
  "source_system": "aic",
  "license": "public domain",
  "description": "E-12: English Drawing Room of the Georgian Period, c. 1800 — Narcissa Niblack Thorne",
  "concepts": [],
  "visual_motifs": [],
  "style": [],
  "mood": [],
  "entities_depicted": [],
  "color_palette": [],
  "composition": "",
  "notes": ""
}