{
  "id": "art_commons_file_kalika_mata_temple_pavagarh_jpg",
  "title": "Kalika Mata Temple, Pavagarh.jpg",
  "image_url": "https://upload.wikimedia.org/wikipedia/commons/3/32/Kalika_Mata_Temple%2C_Pavagarh.jpg",
  "artist": "<a href=\"//commons.wikimedia.org/wiki/User:Kridha20\" title=\"User:Kridha20\">Kridha20</a>",
  "date": "2023-02-20 13:28:47",
  "source_url": "https://commons.wikimedia.org/wiki/File:Kalika Mata Temple, Pavagarh.jpg",
  "source_system": "commons",
  "license": "Creative Commons Attribution-Share Alike 4.0",
  "description": "Kalika mata temple, Pavagarh",
  "concepts": [],
  "visual_motifs": [],
  "style": [],
  "mood": [],
  "entities_depicted": [],
  "color_palette": [],
  "composition": "",
  "notes": ""
}