{
  "work_id": "work:t2-pubmed-immediate-effect-of-nada-yoga-meditation-on-energy-levels-an",
  "schema_version": 2,
  "title": "Immediate Effect of Nada Yoga Meditation on Energy Levels and Alignment of Seven Chakras as Assessed by Electro-photonic Imaging: A Randomized Controlled Crossover Pilot Study.",
  "authors": [
    {
      "name": "Veerabrahmachar R"
    },
    {
      "name": "Bista S"
    },
    {
      "name": "Bokde R"
    },
    {
      "name": "Jasti N"
    },
    {
      "name": "Bhargav H"
    }
  ],
  "publication": {
    "year": 2023,
    "journal": "Adv Mind Body Med",
    "source": "PubMed/MEDLINE",
    "language": "en"
  },
  "identifiers": {
    "pmid": "37119541",
    "doi": ""
  },
  "topics": [
    "phase-3-heat-fire",
    "frontier_science",
    "bridge_paper"
  ],
  "assets": {
    "pdf_path": null,
    "source_url": "https://pubmed.ncbi.nlm.nih.gov/37119541/",
    "abstract": "Nada Yoga is a branch of yoga philosophy that means \"union through sound.\" The practice involves the resonance of energy centers in the body through specific sound frequencies. These subtle effects of yogic sound resonance on the subtle energy systems of the body have not been assessed before. To investigate the immediate effect of Nada Yoga meditation on the energy levels and alignment of the seven chakras in healthy volunteers. Randomized controlled crossover design. Department of Integrative "
  },
  "provenance": {
    "access_status": "open",
    "oa_status": "green",
    "source": "pubmed_alt17_acquisition",
    "retrieved_at": "2026-07-12"
  },
  "phase_mapping": {
    "phase": 3,
    "phase_name": "Heat/Fire",
    "bridge_rationale": "Bridge paper score=17.5: links Heat/Fire concept to mechanistic neuroscience"
  },
  "evaluation": "Score 17: Excellent bridge signal",
  "tier": 2
}