{
  "work_id": "work:t2-pubmed-visual-mental-imagery-evidence-for-a-heterarchical-neural-architecture",
  "schema_version": 2,
  "title": "Visual mental imagery: Evidence for a heterarchical neural architecture.",
  "publication": {
    "year": 2024,
    "type": "article",
    "source": "PubMed/MEDLINE",
    "language": "en",
    "journal": "Phys Life Rev"
  },
  "identifiers": {
    "pmid": "38217888",
    "doi": "10.1016/j.plrev.2023.12.012"
  },
  "topics": [
    "phase-10-imaginal-reconstruction",
    "frontier_science",
    "bridge_paper"
  ],
  "tradition": [
    "contemporary_science"
  ],
  "tier": 2,
  "assets": {
    "pdf_path": null,
    "source_url": "https://pubmed.ncbi.nlm.nih.gov/38217888/",
    "abstract": "Theories of Visual Mental Imagery (VMI) emphasize the processes of retrieval, modification, and recombination of sensory information from long-term memory. Yet, only few studies have focused on the behavioral mechanisms and neural correlates supporting VMI of stimuli from different semantic domains. Therefore, we currently have a limited understanding of how the brain generates and maintains mental representations of colors, faces, shapes - to name a few. Such an undetermined scenario renders un"
  },
  "provenance": {
    "access_status": "open",
    "oa_status": "green",
    "source": "pubmed_t2_search",
    "retrieved_at": "2026-07-12"
  },
  "phase_mapping": {
    "phase": 10,
    "phase_name": "Imaginal Reconstruction",
    "bridge_rationale": "Imaginal — mental imagery as real perception, imagination activating sensory cortices, aphantasia."
  },
  "evaluation": "Good (score=2.5)"
}