{
  "work_id": "work:t2-pubmed-the-role-of-the-dorsolateral-prefrontal-cortex-in-ego-dissol",
  "schema_version": 2,
  "title": "The Role of the Dorsolateral Prefrontal Cortex in Ego Dissolution and Emotional Arousal During the Psychedelic State.",
  "authors": [
    {
      "name": "Coleman CR"
    },
    {
      "name": "Shinozuka K"
    },
    {
      "name": "Tromm R"
    },
    {
      "name": "Dipasquale O"
    },
    {
      "name": "Kaelen M"
    }
  ],
  "publication": {
    "year": 2025,
    "type": "article",
    "source": "PubMed/MEDLINE",
    "language": "en",
    "journal": "Hum Brain Mapp"
  },
  "identifiers": {
    "pmid": "40200796",
    "doi": "10.1002/hbm.70209"
  },
  "topics": [
    "phase-15-the-role-of-the-dors",
    "frontier_science",
    "bridge_paper"
  ],
  "tradition": [
    "contemporary_science"
  ],
  "tier": 2,
  "assets": {
    "pdf_path": "t2-PMC11979361_The_Role_of_the_Dorsolateral_Prefrontal.pdf",
    "source_url": "https://pubmed.ncbi.nlm.nih.gov/40200796/",
    "abstract": "Lysergic acid diethylamide (LSD) is a classic serotonergic psychedelic that induces a profoundly altered conscious state. In conjunction with psychological support, it is currently being explored as a treatment for generalized anxiety disorder and depression. The dorsolateral prefrontal cortex (DLPFC) is a brain region that is known to be involved in mood regulation and disorders; hypofunction in the left DLPFC is associated with depression. This study investigated the role of the DLPFC in the p"
  },
  "provenance": {
    "access_status": "open",
    "oa_status": "green",
    "source": "pubmed_t2_search",
    "retrieved_at": "2026-07-12"
  },
  "phase_mapping": {
    "phase": 15,
    "phase_name": "Liberation/Enlightenment",
    "bridge_rationale": "Liberation and enlightenment \u2014 ego dissolution, self-transcendence, psychedelic-induced mystical experience, spiritual awakening, enlightenment neuroscience."
  },
  "evaluation": "Excellent (score=9.0)"
}