{
  "work_id": "work:t2-pubmed-self-transcending-meditation-is-good-for-mental-health-why-t",
  "schema_version": 2,
  "title": "Self-transcending meditation is good for mental health: why this should be the case.",
  "authors": [
    {
      "name": "Hankey A"
    },
    {
      "name": "Shetkar R"
    }
  ],
  "publication": {
    "year": 2016,
    "journal": "Int Rev Psychiatry",
    "source": "PubMed/MEDLINE",
    "language": "en"
  },
  "identifiers": {
    "pmid": "27329827",
    "doi": "10.1080/09540261.2016.1191449"
  },
  "topics": [
    "phase-16-nondual-unity",
    "frontier_science",
    "bridge_paper"
  ],
  "assets": {
    "pdf_path": null,
    "source_url": "https://pubmed.ncbi.nlm.nih.gov/27329827/",
    "abstract": "A simple theory of health has recently been proposed: while poor quality regulation corresponds to poor quality health so that improving regulation should improve health, optimal regulation optimizes function and optimizes health. Examining the term 'optimal regulation' in biological systems leads to a straightforward definition in terms of 'criticality' in complexity biology, a concept that seems to apply universally throughout biology. Criticality maximizes information processing and sensitivi"
  },
  "provenance": {
    "access_status": "open",
    "oa_status": "green",
    "source": "pubmed_alt17_acquisition",
    "retrieved_at": "2026-07-12"
  },
  "phase_mapping": {
    "phase": 16,
    "phase_name": "Nondual/Unity",
    "bridge_rationale": "Bridge paper score=11.0: links Nondual/Unity concept to mechanistic neuroscience"
  },
  "evaluation": "Score 11: Excellent bridge signal",
  "tier": 2
}