{
  "author_id": "author:henry-corbin",
  "name": "Henry Corbin",
  "born": 1903,
  "died": 1978,
  "tradition": ["shii_islam", "sufism", "iranian_philosophy", "phenomenology", "hermeneutics"],
  "works": [
    "work:corbin-mundus-imaginalis",
    "work:corbin-temple-contemplation"
  ],
  "description": "French philosopher, theologian, and professor of Islamic studies, best known for his work on Iranian philosophy, Sufism, and the concept of the mundus imaginalis.",
  "key_concepts": ["mundus_imaginalis", "active_imagination", "theophanic_imagination", "ta_wil"]
}
